django_ckeditor_youtube_plugin/__init__.py
django_ckeditor_youtube_plugin/apps.py
django_ckeditor_youtube_plugin/static/ckeditor/ckeditor/plugins/youtube/plugin.js
django_ckeditor_youtube_plugin/static/ckeditor/ckeditor/plugins/youtube/plugin.min.js
django_ckeditor_youtube_plugin/static/ckeditor/ckeditor/plugins/youtube/images/icon-hdpi.png
django_ckeditor_youtube_plugin/static/ckeditor/ckeditor/plugins/youtube/images/icon.png
django_ckeditor_youtube_plugin/static/ckeditor/ckeditor/plugins/youtube/lang/ar.js
django_ckeditor_youtube_plugin/static/ckeditor/ckeditor/plugins/youtube/lang/ar.min.js
django_ckeditor_youtube_plugin/static/ckeditor/ckeditor/plugins/youtube/lang/bg.js
django_ckeditor_youtube_plugin/static/ckeditor/ckeditor/plugins/youtube/lang/bg.min.js
django_ckeditor_youtube_plugin/static/ckeditor/ckeditor/plugins/youtube/lang/cs.js
django_ckeditor_youtube_plugin/static/ckeditor/ckeditor/plugins/youtube/lang/cs.min.js
django_ckeditor_youtube_plugin/static/ckeditor/ckeditor/plugins/youtube/lang/de.js
django_ckeditor_youtube_plugin/static/ckeditor/ckeditor/plugins/youtube/lang/de.min.js
django_ckeditor_youtube_plugin/static/ckeditor/ckeditor/plugins/youtube/lang/el.js
django_ckeditor_youtube_plugin/static/ckeditor/ckeditor/plugins/youtube/lang/el.min.js
django_ckeditor_youtube_plugin/static/ckeditor/ckeditor/plugins/youtube/lang/en.js
django_ckeditor_youtube_plugin/static/ckeditor/ckeditor/plugins/youtube/lang/en.min.js
django_ckeditor_youtube_plugin/static/ckeditor/ckeditor/plugins/youtube/lang/es.js
django_ckeditor_youtube_plugin/static/ckeditor/ckeditor/plugins/youtube/lang/es.min.js
django_ckeditor_youtube_plugin/static/ckeditor/ckeditor/plugins/youtube/lang/et.js
django_ckeditor_youtube_plugin/static/ckeditor/ckeditor/plugins/youtube/lang/et.min.js
django_ckeditor_youtube_plugin/static/ckeditor/ckeditor/plugins/youtube/lang/eu.js
django_ckeditor_youtube_plugin/static/ckeditor/ckeditor/plugins/youtube/lang/eu.min.js
django_ckeditor_youtube_plugin-0.0.1.dist-info/LICENSE
django_ckeditor_youtube_plugin-0.0.1.dist-info/METADATA
django_ckeditor_youtube_plugin-0.0.1.dist-info/WHEEL
django_ckeditor_youtube_plugin-0.0.1.dist-info/top_level.txt
django_ckeditor_youtube_plugin-0.0.1.dist-info/RECORD
